pdfslides/__init__.py
pdfslides/__main__.py
pdfslides/cli.py
pdfslides-1.0.1.dist-info/METADATA
pdfslides-1.0.1.dist-info/WHEEL
pdfslides-1.0.1.dist-info/entry_points.txt
pdfslides-1.0.1.dist-info/top_level.txt
pdfslides-1.0.1.dist-info/RECORD
