Metadata-Version: 2.2
Name: pdfslides
Version: 1.0.1
Summary: A tool to convert PDF files into PowerPoint presentations.
Author-email: Jia Sun <sun1011jacobi@gmail.com>
License: MIT
Requires-Python: >=3.6
Requires-Dist: pymupdf
Requires-Dist: python-pptx
